strfix/__init__.py
strfix/_modidx.py
strfix/core.py
strfix/fixs.py
strfix-0.0.1.dist-info/LICENSE
strfix-0.0.1.dist-info/METADATA
strfix-0.0.1.dist-info/WHEEL
strfix-0.0.1.dist-info/entry_points.txt
strfix-0.0.1.dist-info/top_level.txt
strfix-0.0.1.dist-info/RECORD
